meow/__init__.py
meow/arrays.py
meow/base_model.py
meow/cache.py
meow/cell.py
meow/cross_section.py
meow/environment.py
meow/gds_structures.py
meow/geometries.py
meow/integrate.py
meow/materials.py
meow/mesh.py
meow/mode.py
meow/structures.py
meow/visualize.py
meow/assets/silicon.csv
meow/assets/silicon_oxide.csv
meow/eme/__init__.py
meow/eme/common.py
meow/eme/propagate.py
meow/eme/sax.py
meow/fde/__init__.py
meow/fde/lumerical.py
meow/fde/tidy3d.py
meow_sim-0.14.1.dist-info/licenses/LICENSE
tests/mode_data.py
tests/test_deserialization.py
tests/test_mode_operators.py
tests/test_nbs.py
tests/test_propagation.py
meow_sim-0.14.1.dist-info/METADATA
meow_sim-0.14.1.dist-info/WHEEL
meow_sim-0.14.1.dist-info/top_level.txt
meow_sim-0.14.1.dist-info/RECORD
